edolview.py
edolview-0.1.3.dist-info/METADATA
edolview-0.1.3.dist-info/WHEEL
edolview-0.1.3.dist-info/top_level.txt
edolview-0.1.3.dist-info/RECORD
