Metadata-Version: 2.4
Name: edolview
Version: 0.1.3
Summary: A remote tool for edolview
Author-email: Daniel Jeon <edoli.mia@gmail.com>
License: MIT
Project-URL: Homepage, https://github.com/edoli/edolview-rs
Keywords: util,edolview
Requires-Python: >=3.8
Requires-Dist: numpy
